{"data":{"rows":{"0":{"cells":[{"content":"United States"},{"content":"78,430"},{"content":"65.64"},{"content":"251.40"},{"content":"5.38"}]},"1":{"cells":[{"content":"United Kingdom"},{"content":"9,500"},{"content":"7.92"},{"content":"155.20"},{"content":"3.56"}]},"2":{"cells":[{"content":"Germany"},{"content":"4,350"},{"content":"3.64"},{"content":"52.90"},{"content":"1.19"}]},"3":{"cells":[{"content":"France"},{"content":"3,750"},{"content":"3.14"},{"content":"58.70"},{"content":"1.31"}]},"4":{"cells":[{"content":"Italy"},{"content":"3,300"},{"content":"2.76"},{"content":"55.40"},{"content":"1.43"}]},"5":{"cells":[{"content":"Canada"},{"content":"2,830"},{"content":"2.37"},{"content":"85.00"},{"content":"1.88"}]},"6":{"cells":[{"content":"Poland"},{"content":"2,500"},{"content":"2.09"},{"content":"65.60"},{"content":"4.74"}]},"7":{"cells":[{"content":"Turkey"},{"content":"1,710"},{"content":"1.43"},{"content":"23.10"},{"content":"2.31"}]},"8":{"cells":[{"content":"Australia"},{"content":"1,550"},{"content":"1.30"},{"content":"73.50"},{"content":"1.52"}]},"9":{"cells":[{"content":"Spain"},{"content":"1,415"},{"content":"1.18"},{"content":"31.80"},{"content":"0.88"}]},"10":{"cells":[{"content":"Romania"},{"content":"1,140"},{"content":"0.95"},{"content":"53.30"},{"content":"5.61"}]},"11":{"cells":[{"content":"Georgia"},{"content":"925"},{"content":"0.77"},{"content":"214.60"},{"content":"72.32"}]},"12":{"cells":[{"content":"Denmark"},{"content":"750"},{"content":"0.63"},{"content":"137.40"},{"content":"2.20"}]},"13":{"cells":[{"content":"Belgium"},{"content":"590"},{"content":"0.49"},{"content":"55.70"},{"content":"1.17"}]},"14":{"cells":[{"content":"Bulgaria"},{"content":"525"},{"content":"0.44"},{"content":"69.20"},{"content":"10.52"}]},"15":{"cells":[{"content":"Czech Republic"},{"content":"525"},{"content":"0.44"},{"content":"51.00"},{"content":"2.42"}]},"17":{"cells":[{"content":"Sweden"},{"content":"500"},{"content":"0.42"},{"content":"54.30"},{"content":"1.04"}]},"16":{"cells":[{"content":"Norway"},{"content":"500"},{"content":"0.42"},{"content":"104.80"},{"content":"1.11"}]},"19":{"cells":[{"content":"Slovakia"},{"content":"290"},{"content":"0.24"},{"content":"53.70"},{"content":"3.05"}]},"18":{"cells":[{"content":"Hungary"},{"content":"340"},{"content":"0.29"},{"content":"34.00"},{"content":"2.20"}]},"21":{"cells":[{"content":"Portugal"},{"content":"265"},{"content":"0.22"},{"content":"24.80"},{"content":"1.09"}]},"20":{"cells":[{"content":"Croatia"},{"content":"280"},{"content":"0.23"},{"content":"63.30"},{"content":"4.04"}]},"23":{"cells":[{"content":"Lithuania"},{"content":"245"},{"content":"0.21"},{"content":"73.80"},{"content":"5.18"}]},"22":{"cells":[{"content":"Albania"},{"content":"250"},{"content":"0.21"},{"content":"79.60"},{"content":"19.05"}]},"25":{"cells":[{"content":"Latvia"},{"content":"170"},{"content":"0.14"},{"content":"75.20"},{"content":"5.03"}]},"24":{"cells":[{"content":"Macedonia [FYROM]"},{"content":"210"},{"content":"0.18"},{"content":"102.90"},{"content":"23.35"}]},"27":{"cells":[{"content":"New Zealand"},{"content":"155"},{"content":"0.13"},{"content":"36.60"},{"content":"1.23"}]},"26":{"cells":[{"content":"Estonia"},{"content":"160"},{"content":"0.13"},{"content":"119.40"},{"content":"6.90"}]},"29":{"cells":[{"content":"Azerbaijan"},{"content":"90"},{"content":"0.08"},{"content":"10.30"},{"content":"2.01"}]},"28":{"cells":[{"content":"Finland"},{"content":"115"},{"content":"0.10"},{"content":"21.70"},{"content":"0.42"}]},"31":{"cells":[{"content":"Greece"},{"content":"75"},{"content":"0.06"},{"content":"6.80"},{"content":"0.21"}]},"30":{"cells":[{"content":"Slovenia"},{"content":"75"},{"content":"0.06"},{"content":"37.10"},{"content":"1.38"}]},"34":{"cells":[{"content":"Singapore"},{"content":"40"},{"content":"0.03"},{"content":"8.70"},{"content":"0.22"}]},"35":{"cells":[{"content":"Montenegro"},{"content":"30"},{"content":"0.03"},{"content":"48.20"},{"content":"6.22"}]},"32":{"cells":[{"content":"Armenia"},{"content":"40"},{"content":"0.03"},{"content":"24.40"},{"content":"6.29"}]},"33":{"cells":[{"content":"Mongolia"},{"content":"40"},{"content":"0.03"},{"content":"15.20"},{"content":"7.61"}]},"38":{"cells":[{"content":"Luxembourg"},{"content":"9"},{"content":"0.01"},{"content":"18.70"},{"content":"0.17"}]},"39":{"cells":[{"content":"Bosnia and Herzegovina"},{"content":"10"},{"content":"0.01"},{"content":"2.70"},{"content":"0.54"}]},"36":{"cells":[{"content":"United Arab Emirates"},{"content":"25"},{"content":"0.02"},{"content":"5.60"},{"content":"0.09"}]},"37":{"cells":[{"content":"Ukraine"},{"content":"15"},{"content":"0.01"},{"content":"0.30"},{"content":"0.08"}]},"42":{"cells":[{"content":"Iceland"},{"content":"3"},{"content":"0.00"},{"content":"9.50"},{"content":"0.18"}]},"43":{"cells":[{"content":"Austria"},{"content":"3"},{"content":"0.00"},{"content":"0.40"},{"content":"0.01"}]},"40":{"cells":[{"content":"Ireland"},{"content":"7"},{"content":"0.01"},{"content":"1.60"},{"content":"0.03"}]},"41":{"cells":[{"content":"Jordan"},{"content":"6"},{"content":"0.01"},{"content":"1.00"},{"content":"0.28"}]},"44":{"cells":[{"content":"No Results"},{"content":"No Results"},{"content":"No Results"},{"content":"No Results"},{"content":"No Results"}]}},"columns":{"0":{"cells":[{"content":"United States"},{"content":"United Kingdom"},{"content":"Germany"},{"content":"France"},{"content":"Italy"},{"content":"Canada"},{"content":"Poland"},{"content":"Turkey"},{"content":"Australia"},{"content":"Spain"},{"content":"Romania"},{"content":"Georgia"},{"content":"Denmark"},{"content":"Belgium"},{"content":"Bulgaria"},{"content":"Czech Republic"},{"content":"Norway"},{"content":"Sweden"},{"content":"Hungary"},{"content":"Slovakia"},{"content":"Croatia"},{"content":"Portugal"},{"content":"Albania"},{"content":"Lithuania"},{"content":"Macedonia [FYROM]"},{"content":"Latvia"},{"content":"Estonia"},{"content":"New Zealand"},{"content":"Finland"},{"content":"Azerbaijan"},{"content":"Slovenia"},{"content":"Greece"},{"content":"Armenia"},{"content":"Mongolia"},{"content":"Singapore"},{"content":"Montenegro"},{"content":"United Arab Emirates"},{"content":"Ukraine"},{"content":"Luxembourg"},{"content":"Bosnia and Herzegovina"},{"content":"Ireland"},{"content":"Jordan"},{"content":"Iceland"},{"content":"Austria"},{"content":"No Results"}]},"1":{"cells":[{"content":"78,430"},{"content":"9,500"},{"content":"4,350"},{"content":"3,750"},{"content":"3,300"},{"content":"2,830"},{"content":"2,500"},{"content":"1,710"},{"content":"1,550"},{"content":"1,415"},{"content":"1,140"},{"content":"925"},{"content":"750"},{"content":"590"},{"content":"525"},{"content":"525"},{"content":"500"},{"content":"500"},{"content":"340"},{"content":"290"},{"content":"280"},{"content":"265"},{"content":"250"},{"content":"245"},{"content":"210"},{"content":"170"},{"content":"160"},{"content":"155"},{"content":"115"},{"content":"90"},{"content":"75"},{"content":"75"},{"content":"40"},{"content":"40"},{"content":"40"},{"content":"30"},{"content":"25"},{"content":"15"},{"content":"9"},{"content":"10"},{"content":"7"},{"content":"6"},{"content":"3"},{"content":"3"},{"content":"No Results"}]},"2":{"cells":[{"content":"65.64"},{"content":"7.92"},{"content":"3.64"},{"content":"3.14"},{"content":"2.76"},{"content":"2.37"},{"content":"2.09"},{"content":"1.43"},{"content":"1.30"},{"content":"1.18"},{"content":"0.95"},{"content":"0.77"},{"content":"0.63"},{"content":"0.49"},{"content":"0.44"},{"content":"0.44"},{"content":"0.42"},{"content":"0.42"},{"content":"0.29"},{"content":"0.24"},{"content":"0.23"},{"content":"0.22"},{"content":"0.21"},{"content":"0.21"},{"content":"0.18"},{"content":"0.14"},{"content":"0.13"},{"content":"0.13"},{"content":"0.10"},{"content":"0.08"},{"content":"0.06"},{"content":"0.06"},{"content":"0.03"},{"content":"0.03"},{"content":"0.03"},{"content":"0.03"},{"content":"0.02"},{"content":"0.01"},{"content":"0.01"},{"content":"0.01"},{"content":"0.01"},{"content":"0.01"},{"content":"0.00"},{"content":"0.00"},{"content":"No Results"}]},"3":{"cells":[{"content":"251.40"},{"content":"155.20"},{"content":"52.90"},{"content":"58.70"},{"content":"55.40"},{"content":"85.00"},{"content":"65.60"},{"content":"23.10"},{"content":"73.50"},{"content":"31.80"},{"content":"53.30"},{"content":"214.60"},{"content":"137.40"},{"content":"55.70"},{"content":"69.20"},{"content":"51.00"},{"content":"104.80"},{"content":"54.30"},{"content":"34.00"},{"content":"53.70"},{"content":"63.30"},{"content":"24.80"},{"content":"79.60"},{"content":"73.80"},{"content":"102.90"},{"content":"75.20"},{"content":"119.40"},{"content":"36.60"},{"content":"21.70"},{"content":"10.30"},{"content":"37.10"},{"content":"6.80"},{"content":"24.40"},{"content":"15.20"},{"content":"8.70"},{"content":"48.20"},{"content":"5.60"},{"content":"0.30"},{"content":"18.70"},{"content":"2.70"},{"content":"1.60"},{"content":"1.00"},{"content":"9.50"},{"content":"0.40"},{"content":"No Results"}]},"4":{"cells":[{"content":"5.38"},{"content":"3.56"},{"content":"1.19"},{"content":"1.31"},{"content":"1.43"},{"content":"1.88"},{"content":"4.74"},{"content":"2.31"},{"content":"1.52"},{"content":"0.88"},{"content":"5.61"},{"content":"72.32"},{"content":"2.20"},{"content":"1.17"},{"content":"10.52"},{"content":"2.42"},{"content":"1.11"},{"content":"1.04"},{"content":"2.20"},{"content":"3.05"},{"content":"4.04"},{"content":"1.09"},{"content":"19.05"},{"content":"5.18"},{"content":"23.35"},{"content":"5.03"},{"content":"6.90"},{"content":"1.23"},{"content":"0.42"},{"content":"2.01"},{"content":"1.38"},{"content":"0.21"},{"content":"6.29"},{"content":"7.61"},{"content":"0.22"},{"content":"6.22"},{"content":"0.09"},{"content":"0.08"},{"content":"0.17"},{"content":"0.54"},{"content":"0.03"},{"content":"0.28"},{"content":"0.18"},{"content":"0.01"},{"content":"No Results"}]}}},"tableId":"countries troops in ISAF.html-0","results":{},"expectedResult":{"columns":{"0":true},"rows":{}},"originalDescription":{"hasContentTables":false,"hasRelevantTables":false}}