{"data":{"rows":{"0":{"cells":[{"content":"Costa Rica"},{"content":"1"},{"content":"76.12"},{"content":"2009"}]},"1":{"cells":[{"content":"Dominican Republic"},{"content":"2"},{"content":"71.78"},{"content":"2009"}]},"2":{"cells":[{"content":"Jamaica"},{"content":"3"},{"content":"70.09"},{"content":"2009"}]},"3":{"cells":[{"content":"Guatemala"},{"content":"4"},{"content":"68.37"},{"content":"2009"}]},"4":{"cells":[{"content":"Vietnam"},{"content":"5"},{"content":"66.52"},{"content":"2009"}]},"5":{"cells":[{"content":"Colombia"},{"content":"6"},{"content":"66.10"},{"content":"2009"}]},"6":{"cells":[{"content":"Cuba"},{"content":"7"},{"content":"65.68"},{"content":"2009"}]},"7":{"cells":[{"content":"El Salvador"},{"content":"8"},{"content":"61.46"},{"content":"2009"}]},"8":{"cells":[{"content":"Brazil"},{"content":"9"},{"content":"61.01"},{"content":"2009"}]},"9":{"cells":[{"content":"Honduras"},{"content":"10"},{"content":"60.99"},{"content":"2009"}]},"10":{"cells":[{"content":"Nicaragua"},{"content":"11"},{"content":"60.54"},{"content":"2009"}]},"11":{"cells":[{"content":"Egypt"},{"content":"12"},{"content":"60.32"},{"content":"2009"}]},"12":{"cells":[{"content":"Saudi Arabia"},{"content":"13"},{"content":"59.70"},{"content":"2009"}]},"13":{"cells":[{"content":"Philippines"},{"content":"14"},{"content":"59.02"},{"content":"2009"}]},"14":{"cells":[{"content":"Argentina"},{"content":"15"},{"content":"58.95"},{"content":"2009"}]},"15":{"cells":[{"content":"Indonesia"},{"content":"16"},{"content":"58.92"},{"content":"2009"}]},"17":{"cells":[{"content":"Panama"},{"content":"18"},{"content":"57.37"},{"content":"2009"}]},"16":{"cells":[{"content":"Bhutan"},{"content":"17"},{"content":"58.50"},{"content":"2009"}]},"19":{"cells":[{"content":"China"},{"content":"20"},{"content":"57.11"},{"content":"2009"}]},"18":{"cells":[{"content":"Laos"},{"content":"19"},{"content":"57.34"},{"content":"2009"}]},"21":{"cells":[{"content":"Sri Lanka"},{"content":"22"},{"content":"56.55"},{"content":"2009"}]},"20":{"cells":[{"content":"Morocco"},{"content":"21"},{"content":"56.75"},{"content":"2009"}]},"23":{"cells":[{"content":"Pakistan"},{"content":"24"},{"content":"55.56"},{"content":"2009"}]},"22":{"cells":[{"content":"Mexico"},{"content":"23"},{"content":"55.58"},{"content":"2009"}]},"25":{"cells":[{"content":"Jordan"},{"content":"26"},{"content":"54.59"},{"content":"2009"}]},"24":{"cells":[{"content":"Ecuador"},{"content":"25"},{"content":"55.46"},{"content":"2009"}]},"27":{"cells":[{"content":"Peru"},{"content":"28"},{"content":"54.37"},{"content":"2009"}]},"26":{"cells":[{"content":"Belize"},{"content":"27"},{"content":"54.53"},{"content":"2009"}]},"29":{"cells":[{"content":"Trinidad and Tobago"},{"content":"30"},{"content":"54.21"},{"content":"2009"}]},"28":{"cells":[{"content":"Tunisia"},{"content":"29"},{"content":"54.31"},{"content":"2009"}]},"31":{"cells":[{"content":"Moldova"},{"content":"32"},{"content":"54.08"},{"content":"2009"}]},"30":{"cells":[{"content":"Bangladesh"},{"content":"31"},{"content":"54.09"},{"content":"2009"}]},"34":{"cells":[{"content":"India"},{"content":"35"},{"content":"53.03"},{"content":"2009"}]},"35":{"cells":[{"content":"Venezuela"},{"content":"36"},{"content":"52.49"},{"content":"2009"}]},"32":{"cells":[{"content":"Malaysia"},{"content":"33"},{"content":"54.05"},{"content":"2009"}]},"33":{"cells":[{"content":"Tajikistan"},{"content":"34"},{"content":"53.48"},{"content":"2009"}]},"38":{"cells":[{"content":"Burma"},{"content":"39"},{"content":"51.23"},{"content":"2009"}]},"39":{"cells":[{"content":"Algeria"},{"content":"40"},{"content":"51.23"},{"content":"2009"}]},"36":{"cells":[{"content":"Nepal"},{"content":"37"},{"content":"51.91"},{"content":"2009"}]},"37":{"cells":[{"content":"Syria"},{"content":"38"},{"content":"51.32"},{"content":"2009"}]},"42":{"cells":[{"content":"Netherlands"},{"content":"43"},{"content":"50.60"},{"content":"2009"}]},"43":{"cells":[{"content":"Malta"},{"content":"44"},{"content":"50.36"},{"content":"2009"}]},"40":{"cells":[{"content":"Thailand"},{"content":"41"},{"content":"50.90"},{"content":"2009"}]},"41":{"cells":[{"content":"Haiti"},{"content":"42"},{"content":"50.84"},{"content":"2009"}]},"46":{"cells":[{"content":"Bolivia"},{"content":"47"},{"content":"49.35"},{"content":"2009"}]},"47":{"cells":[{"content":"Armenia"},{"content":"48"},{"content":"48.28"},{"content":"2009"}]},"44":{"cells":[{"content":"Uzbekistan"},{"content":"45"},{"content":"50.07"},{"content":"2009"}]},"45":{"cells":[{"content":"Chile"},{"content":"46"},{"content":"49.72"},{"content":"2009"}]},"51":{"cells":[{"content":"Switzerland"},{"content":"52"},{"content":"48.05"},{"content":"2009"}]},"50":{"cells":[{"content":"Germany"},{"content":"51"},{"content":"48.07"},{"content":"2009"}]},"49":{"cells":[{"content":"Yemen"},{"content":"50"},{"content":"48.09"},{"content":"2009"}]},"48":{"cells":[{"content":"Singapore"},{"content":"49"},{"content":"48.24"},{"content":"2009"}]},"55":{"cells":[{"content":"Palestine"},{"content":"56"},{"content":"47.73"},{"content":"2009"}]},"54":{"cells":[{"content":"Paraguay"},{"content":"55"},{"content":"47.80"},{"content":"2009"}]},"53":{"cells":[{"content":"Albania"},{"content":"54"},{"content":"47.91"},{"content":"2009"}]},"52":{"cells":[{"content":"Sweden"},{"content":"53"},{"content":"47.99"},{"content":"2009"}]},"59":{"cells":[{"content":"Croatia"},{"content":"60"},{"content":"47.23"},{"content":"2009"}]},"58":{"cells":[{"content":"Finland"},{"content":"59"},{"content":"47.23"},{"content":"2009"}]},"57":{"cells":[{"content":"Serbia"},{"content":"58"},{"content":"47.63"},{"content":"2009"}]},"56":{"cells":[{"content":"Austria"},{"content":"57"},{"content":"47.69"},{"content":"2009"}]},"63":{"cells":[{"content":"Belgium"},{"content":"64"},{"content":"45.36"},{"content":"2009"}]},"62":{"cells":[{"content":"Guyana"},{"content":"63"},{"content":"45.63"},{"content":"2009"}]},"61":{"cells":[{"content":"Cyprus"},{"content":"62"},{"content":"46.19"},{"content":"2009"}]},"60":{"cells":[{"content":"Kyrgyzstan"},{"content":"61"},{"content":"47.09"},{"content":"2009"}]},"68":{"cells":[{"content":"Italy"},{"content":"69"},{"content":"44.02"},{"content":"2009"}]},"69":{"cells":[{"content":"Romania"},{"content":"70"},{"content":"43.89"},{"content":"2009"}]},"70":{"cells":[{"content":"France"},{"content":"71"},{"content":"43.86"},{"content":"2009"}]},"71":{"cells":[{"content":"Georgia"},{"content":"72"},{"content":"43.60"},{"content":"2009"}]},"64":{"cells":[{"content":"Bosnia and Herzegovina"},{"content":"65"},{"content":"44.96"},{"content":"2009"}]},"65":{"cells":[{"content":"Slovenia"},{"content":"66"},{"content":"44.53"},{"content":"2009"}]},"66":{"cells":[{"content":"Israel"},{"content":"67"},{"content":"44.49"},{"content":"2009"}]},"67":{"cells":[{"content":"Korea, South"},{"content":"68"},{"content":"44.43"},{"content":"2009"}]},"76":{"cells":[{"content":"Poland"},{"content":"77"},{"content":"42.75"},{"content":"2009"}]},"77":{"cells":[{"content":"Ireland"},{"content":"78"},{"content":"42.62"},{"content":"2009"}]},"78":{"cells":[{"content":"Iraq"},{"content":"79"},{"content":"42.59"},{"content":"2009"}]},"79":{"cells":[{"content":"Cambodia"},{"content":"80"},{"content":"42.34"},{"content":"2009"}]},"72":{"cells":[{"content":"Slovakia"},{"content":"73"},{"content":"43.52"},{"content":"2009"}]},"73":{"cells":[{"content":"United Kingdom"},{"content":"74"},{"content":"43.31"},{"content":"2009"}]},"74":{"cells":[{"content":"Japan"},{"content":"75"},{"content":"43.25"},{"content":"2009"}]},"75":{"cells":[{"content":"Spain"},{"content":"76"},{"content":"43.19"},{"content":"2009"}]},"85":{"cells":[{"content":"Lithuania"},{"content":"86"},{"content":"40.90"},{"content":"2009"}]},"84":{"cells":[{"content":"Azerbaijan"},{"content":"85"},{"content":"41.21"},{"content":"2009"}]},"87":{"cells":[{"content":"Norway"},{"content":"88"},{"content":"40.36"},{"content":"2009"}]},"86":{"cells":[{"content":"Djibouti"},{"content":"87"},{"content":"40.44"},{"content":"2009"}]},"81":{"cells":[{"content":"Bulgaria"},{"content":"82"},{"content":"42.04"},{"content":"2009"}]},"80":{"cells":[{"content":"Iran"},{"content":"81"},{"content":"42.08"},{"content":"2009"}]},"83":{"cells":[{"content":"Hong Kong"},{"content":"84"},{"content":"41.60"},{"content":"2009"}]},"82":{"cells":[{"content":"Turkey"},{"content":"83"},{"content":"41.70"},{"content":"2009"}]},"93":{"cells":[{"content":"Iceland"},{"content":"94"},{"content":"38.14"},{"content":"2009"}]},"92":{"cells":[{"content":"Mauritania"},{"content":"93"},{"content":"38.21"},{"content":"2009"}]},"95":{"cells":[{"content":"Senegal"},{"content":"96"},{"content":"38.03"},{"content":"2009"}]},"94":{"cells":[{"content":"Ukraine"},{"content":"95"},{"content":"38.07"},{"content":"2009"}]},"89":{"cells":[{"content":"Hungary"},{"content":"90"},{"content":"38.86"},{"content":"2009"}]},"88":{"cells":[{"content":"Canada"},{"content":"89"},{"content":"39.40"},{"content":"2009"}]},"91":{"cells":[{"content":"Czech Republic"},{"content":"92"},{"content":"38.31"},{"content":"2009"}]},"90":{"cells":[{"content":"Kazakhstan"},{"content":"91"},{"content":"38.54"},{"content":"2009"}]},"102":{"cells":[{"content":"New Zealand"},{"content":"103"},{"content":"36.21"},{"content":"2009"}]},"103":{"cells":[{"content":"Belarus"},{"content":"104"},{"content":"35.67"},{"content":"2009"}]},"100":{"cells":[{"content":"Latvia"},{"content":"101"},{"content":"36.67"},{"content":"2009"}]},"101":{"cells":[{"content":"Australia"},{"content":"102"},{"content":"36.64"},{"content":"2009"}]},"98":{"cells":[{"content":"Uruguay"},{"content":"99"},{"content":"37.24"},{"content":"2009"}]},"99":{"cells":[{"content":"Ghana"},{"content":"100"},{"content":"37.10"},{"content":"2009"}]},"96":{"cells":[{"content":"Greece"},{"content":"97"},{"content":"37.58"},{"content":"2009"}]},"97":{"cells":[{"content":"Portugal"},{"content":"98"},{"content":"37.46"},{"content":"2009"}]},"110":{"cells":[{"content":"Macedonia [FYROM]"},{"content":"111"},{"content":"32.66"},{"content":"2009"}]},"111":{"cells":[{"content":"Congo, Republic of the"},{"content":"112"},{"content":"32.43"},{"content":"2009"}]},"108":{"cells":[{"content":"Chad"},{"content":"109"},{"content":"34.27"},{"content":"2009"}]},"109":{"cells":[{"content":"Lebanon"},{"content":"110"},{"content":"33.56"},{"content":"2009"}]},"106":{"cells":[{"content":"Malawi"},{"content":"107"},{"content":"34.47"},{"content":"2009"}]},"107":{"cells":[{"content":"Russia"},{"content":"108"},{"content":"34.47"},{"content":"2009"}]},"104":{"cells":[{"content":"Denmark"},{"content":"105"},{"content":"35.47"},{"content":"2009"}]},"105":{"cells":[{"content":"Mongolia"},{"content":"106"},{"content":"34.95"},{"content":"2009"}]},"119":{"cells":[{"content":"Congo, Democratic Republic of the"},{"content":"120"},{"content":"29.04"},{"content":"2009"}]},"118":{"cells":[{"content":"Rwanda"},{"content":"119"},{"content":"29.59"},{"content":"2009"}]},"117":{"cells":[{"content":"South Africa"},{"content":"118"},{"content":"29.69"},{"content":"2009"}]},"116":{"cells":[{"content":"Uganda"},{"content":"117"},{"content":"30.21"},{"content":"2009"}]},"115":{"cells":[{"content":"Guinea"},{"content":"116"},{"content":"30.25"},{"content":"2009"}]},"114":{"cells":[{"content":"Nigeria"},{"content":"115"},{"content":"30.35"},{"content":"2009"}]},"113":{"cells":[{"content":"United States"},{"content":"114"},{"content":"30.73"},{"content":"2009"}]},"112":{"cells":[{"content":"Madagascar"},{"content":"113"},{"content":"31.54"},{"content":"2009"}]},"127":{"cells":[{"content":"Kuwait"},{"content":"128"},{"content":"27.04"},{"content":"2009"}]},"126":{"cells":[{"content":"Zambia"},{"content":"127"},{"content":"27.18"},{"content":"2009"}]},"125":{"cells":[{"content":"Cameroon"},{"content":"126"},{"content":"27.22"},{"content":"2009"}]},"124":{"cells":[{"content":"Kenya"},{"content":"125"},{"content":"27.77"},{"content":"2009"}]},"123":{"cells":[{"content":"Ethiopia"},{"content":"124"},{"content":"28.10"},{"content":"2009"}]},"122":{"cells":[{"content":"United Arab Emirates"},{"content":"123"},{"content":"28.16"},{"content":"2009"}]},"121":{"cells":[{"content":"Luxembourg"},{"content":"122"},{"content":"28.47"},{"content":"2009"}]},"120":{"cells":[{"content":"Sudan"},{"content":"121"},{"content":"28.55"},{"content":"2009"}]},"137":{"cells":[{"content":"Burkina Faso"},{"content":"138"},{"content":"22.40"},{"content":"2009"}]},"136":{"cells":[{"content":"Central African Republic"},{"content":"137"},{"content":"22.88"},{"content":"2009"}]},"139":{"cells":[{"content":"Namibia"},{"content":"140"},{"content":"21.10"},{"content":"2009"}]},"138":{"cells":[{"content":"Burundi"},{"content":"139"},{"content":"21.84"},{"content":"2009"}]},"141":{"cells":[{"content":"Tanzania"},{"content":"142"},{"content":"17.79"},{"content":"2009"}]},"140":{"cells":[{"content":"Botswana"},{"content":"141"},{"content":"20.85"},{"content":"2009"}]},"143":{"cells":[{"content":"No Results"},{"content":"No Results"},{"content":"No Results"},{"content":"No Results"}]},"142":{"cells":[{"content":"Zimbabwe"},{"content":"143"},{"content":"16.59"},{"content":"2009"}]},"129":{"cells":[{"content":"Angola"},{"content":"130"},{"content":"26.78"},{"content":"2009"}]},"128":{"cells":[{"content":"Niger"},{"content":"129"},{"content":"26.94"},{"content":"2009"}]},"131":{"cells":[{"content":"Mali"},{"content":"132"},{"content":"25.77"},{"content":"2009"}]},"130":{"cells":[{"content":"Estonia"},{"content":"131"},{"content":"26.42"},{"content":"2009"}]},"133":{"cells":[{"content":"Benin"},{"content":"134"},{"content":"24.58"},{"content":"2009"}]},"132":{"cells":[{"content":"Mozambique"},{"content":"133"},{"content":"24.61"},{"content":"2009"}]},"135":{"cells":[{"content":"Sierra Leone"},{"content":"136"},{"content":"23.08"},{"content":"2009"}]},"134":{"cells":[{"content":"Togo"},{"content":"135"},{"content":"23.28"},{"content":"2009"}]}},"columns":{"0":{"cells":[{"content":"Costa Rica"},{"content":"Dominican Republic"},{"content":"Jamaica"},{"content":"Guatemala"},{"content":"Vietnam"},{"content":"Colombia"},{"content":"Cuba"},{"content":"El Salvador"},{"content":"Brazil"},{"content":"Honduras"},{"content":"Nicaragua"},{"content":"Egypt"},{"content":"Saudi Arabia"},{"content":"Philippines"},{"content":"Argentina"},{"content":"Indonesia"},{"content":"Bhutan"},{"content":"Panama"},{"content":"Laos"},{"content":"China"},{"content":"Morocco"},{"content":"Sri Lanka"},{"content":"Mexico"},{"content":"Pakistan"},{"content":"Ecuador"},{"content":"Jordan"},{"content":"Belize"},{"content":"Peru"},{"content":"Tunisia"},{"content":"Trinidad and Tobago"},{"content":"Bangladesh"},{"content":"Moldova"},{"content":"Malaysia"},{"content":"Tajikistan"},{"content":"India"},{"content":"Venezuela"},{"content":"Nepal"},{"content":"Syria"},{"content":"Burma"},{"content":"Algeria"},{"content":"Thailand"},{"content":"Haiti"},{"content":"Netherlands"},{"content":"Malta"},{"content":"Uzbekistan"},{"content":"Chile"},{"content":"Bolivia"},{"content":"Armenia"},{"content":"Singapore"},{"content":"Yemen"},{"content":"Germany"},{"content":"Switzerland"},{"content":"Sweden"},{"content":"Albania"},{"content":"Paraguay"},{"content":"Palestine"},{"content":"Austria"},{"content":"Serbia"},{"content":"Finland"},{"content":"Croatia"},{"content":"Kyrgyzstan"},{"content":"Cyprus"},{"content":"Guyana"},{"content":"Belgium"},{"content":"Bosnia and Herzegovina"},{"content":"Slovenia"},{"content":"Israel"},{"content":"Korea, South"},{"content":"Italy"},{"content":"Romania"},{"content":"France"},{"content":"Georgia"},{"content":"Slovakia"},{"content":"United Kingdom"},{"content":"Japan"},{"content":"Spain"},{"content":"Poland"},{"content":"Ireland"},{"content":"Iraq"},{"content":"Cambodia"},{"content":"Iran"},{"content":"Bulgaria"},{"content":"Turkey"},{"content":"Hong Kong"},{"content":"Azerbaijan"},{"content":"Lithuania"},{"content":"Djibouti"},{"content":"Norway"},{"content":"Canada"},{"content":"Hungary"},{"content":"Kazakhstan"},{"content":"Czech Republic"},{"content":"Mauritania"},{"content":"Iceland"},{"content":"Ukraine"},{"content":"Senegal"},{"content":"Greece"},{"content":"Portugal"},{"content":"Uruguay"},{"content":"Ghana"},{"content":"Latvia"},{"content":"Australia"},{"content":"New Zealand"},{"content":"Belarus"},{"content":"Denmark"},{"content":"Mongolia"},{"content":"Malawi"},{"content":"Russia"},{"content":"Chad"},{"content":"Lebanon"},{"content":"Macedonia [FYROM]"},{"content":"Congo, Republic of the"},{"content":"Madagascar"},{"content":"United States"},{"content":"Nigeria"},{"content":"Guinea"},{"content":"Uganda"},{"content":"South Africa"},{"content":"Rwanda"},{"content":"Congo, Democratic Republic of the"},{"content":"Sudan"},{"content":"Luxembourg"},{"content":"United Arab Emirates"},{"content":"Ethiopia"},{"content":"Kenya"},{"content":"Cameroon"},{"content":"Zambia"},{"content":"Kuwait"},{"content":"Niger"},{"content":"Angola"},{"content":"Estonia"},{"content":"Mali"},{"content":"Mozambique"},{"content":"Benin"},{"content":"Togo"},{"content":"Sierra Leone"},{"content":"Central African Republic"},{"content":"Burkina Faso"},{"content":"Burundi"},{"content":"Namibia"},{"content":"Botswana"},{"content":"Tanzania"},{"content":"Zimbabwe"},{"content":"No Results"}]},"1":{"cells":[{"content":"1"},{"content":"2"},{"content":"3"},{"content":"4"},{"content":"5"},{"content":"6"},{"content":"7"},{"content":"8"},{"content":"9"},{"content":"10"},{"content":"11"},{"content":"12"},{"content":"13"},{"content":"14"},{"content":"15"},{"content":"16"},{"content":"17"},{"content":"18"},{"content":"19"},{"content":"20"},{"content":"21"},{"content":"22"},{"content":"23"},{"content":"24"},{"content":"25"},{"content":"26"},{"content":"27"},{"content":"28"},{"content":"29"},{"content":"30"},{"content":"31"},{"content":"32"},{"content":"33"},{"content":"34"},{"content":"35"},{"content":"36"},{"content":"37"},{"content":"38"},{"content":"39"},{"content":"40"},{"content":"41"},{"content":"42"},{"content":"43"},{"content":"44"},{"content":"45"},{"content":"46"},{"content":"47"},{"content":"48"},{"content":"49"},{"content":"50"},{"content":"51"},{"content":"52"},{"content":"53"},{"content":"54"},{"content":"55"},{"content":"56"},{"content":"57"},{"content":"58"},{"content":"59"},{"content":"60"},{"content":"61"},{"content":"62"},{"content":"63"},{"content":"64"},{"content":"65"},{"content":"66"},{"content":"67"},{"content":"68"},{"content":"69"},{"content":"70"},{"content":"71"},{"content":"72"},{"content":"73"},{"content":"74"},{"content":"75"},{"content":"76"},{"content":"77"},{"content":"78"},{"content":"79"},{"content":"80"},{"content":"81"},{"content":"82"},{"content":"83"},{"content":"84"},{"content":"85"},{"content":"86"},{"content":"87"},{"content":"88"},{"content":"89"},{"content":"90"},{"content":"91"},{"content":"92"},{"content":"93"},{"content":"94"},{"content":"95"},{"content":"96"},{"content":"97"},{"content":"98"},{"content":"99"},{"content":"100"},{"content":"101"},{"content":"102"},{"content":"103"},{"content":"104"},{"content":"105"},{"content":"106"},{"content":"107"},{"content":"108"},{"content":"109"},{"content":"110"},{"content":"111"},{"content":"112"},{"content":"113"},{"content":"114"},{"content":"115"},{"content":"116"},{"content":"117"},{"content":"118"},{"content":"119"},{"content":"120"},{"content":"121"},{"content":"122"},{"content":"123"},{"content":"124"},{"content":"125"},{"content":"126"},{"content":"127"},{"content":"128"},{"content":"129"},{"content":"130"},{"content":"131"},{"content":"132"},{"content":"133"},{"content":"134"},{"content":"135"},{"content":"136"},{"content":"137"},{"content":"138"},{"content":"139"},{"content":"140"},{"content":"141"},{"content":"142"},{"content":"143"},{"content":"No Results"}]},"2":{"cells":[{"content":"76.12"},{"content":"71.78"},{"content":"70.09"},{"content":"68.37"},{"content":"66.52"},{"content":"66.10"},{"content":"65.68"},{"content":"61.46"},{"content":"61.01"},{"content":"60.99"},{"content":"60.54"},{"content":"60.32"},{"content":"59.70"},{"content":"59.02"},{"content":"58.95"},{"content":"58.92"},{"content":"58.50"},{"content":"57.37"},{"content":"57.34"},{"content":"57.11"},{"content":"56.75"},{"content":"56.55"},{"content":"55.58"},{"content":"55.56"},{"content":"55.46"},{"content":"54.59"},{"content":"54.53"},{"content":"54.37"},{"content":"54.31"},{"content":"54.21"},{"content":"54.09"},{"content":"54.08"},{"content":"54.05"},{"content":"53.48"},{"content":"53.03"},{"content":"52.49"},{"content":"51.91"},{"content":"51.32"},{"content":"51.23"},{"content":"51.23"},{"content":"50.90"},{"content":"50.84"},{"content":"50.60"},{"content":"50.36"},{"content":"50.07"},{"content":"49.72"},{"content":"49.35"},{"content":"48.28"},{"content":"48.24"},{"content":"48.09"},{"content":"48.07"},{"content":"48.05"},{"content":"47.99"},{"content":"47.91"},{"content":"47.80"},{"content":"47.73"},{"content":"47.69"},{"content":"47.63"},{"content":"47.23"},{"content":"47.23"},{"content":"47.09"},{"content":"46.19"},{"content":"45.63"},{"content":"45.36"},{"content":"44.96"},{"content":"44.53"},{"content":"44.49"},{"content":"44.43"},{"content":"44.02"},{"content":"43.89"},{"content":"43.86"},{"content":"43.60"},{"content":"43.52"},{"content":"43.31"},{"content":"43.25"},{"content":"43.19"},{"content":"42.75"},{"content":"42.62"},{"content":"42.59"},{"content":"42.34"},{"content":"42.08"},{"content":"42.04"},{"content":"41.70"},{"content":"41.60"},{"content":"41.21"},{"content":"40.90"},{"content":"40.44"},{"content":"40.36"},{"content":"39.40"},{"content":"38.86"},{"content":"38.54"},{"content":"38.31"},{"content":"38.21"},{"content":"38.14"},{"content":"38.07"},{"content":"38.03"},{"content":"37.58"},{"content":"37.46"},{"content":"37.24"},{"content":"37.10"},{"content":"36.67"},{"content":"36.64"},{"content":"36.21"},{"content":"35.67"},{"content":"35.47"},{"content":"34.95"},{"content":"34.47"},{"content":"34.47"},{"content":"34.27"},{"content":"33.56"},{"content":"32.66"},{"content":"32.43"},{"content":"31.54"},{"content":"30.73"},{"content":"30.35"},{"content":"30.25"},{"content":"30.21"},{"content":"29.69"},{"content":"29.59"},{"content":"29.04"},{"content":"28.55"},{"content":"28.47"},{"content":"28.16"},{"content":"28.10"},{"content":"27.77"},{"content":"27.22"},{"content":"27.18"},{"content":"27.04"},{"content":"26.94"},{"content":"26.78"},{"content":"26.42"},{"content":"25.77"},{"content":"24.61"},{"content":"24.58"},{"content":"23.28"},{"content":"23.08"},{"content":"22.88"},{"content":"22.40"},{"content":"21.84"},{"content":"21.10"},{"content":"20.85"},{"content":"17.79"},{"content":"16.59"},{"content":"No Results"}]},"3":{"cells":[{"content":"2009"},{"content":"2009"},{"content":"2009"},{"content":"2009"},{"content":"2009"},{"content":"2009"},{"content":"2009"},{"content":"2009"},{"content":"2009"},{"content":"2009"},{"content":"2009"},{"content":"2009"},{"content":"2009"},{"content":"2009"},{"content":"2009"},{"content":"2009"},{"content":"2009"},{"content":"2009"},{"content":"2009"},{"content":"2009"},{"content":"2009"},{"content":"2009"},{"content":"2009"},{"content":"2009"},{"content":"2009"},{"content":"2009"},{"content":"2009"},{"content":"2009"},{"content":"2009"},{"content":"2009"},{"content":"2009"},{"content":"2009"},{"content":"2009"},{"content":"2009"},{"content":"2009"},{"content":"2009"},{"content":"2009"},{"content":"2009"},{"content":"2009"},{"content":"2009"},{"content":"2009"},{"content":"2009"},{"content":"2009"},{"content":"2009"},{"content":"2009"},{"content":"2009"},{"content":"2009"},{"content":"2009"},{"content":"2009"},{"content":"2009"},{"content":"2009"},{"content":"2009"},{"content":"2009"},{"content":"2009"},{"content":"2009"},{"content":"2009"},{"content":"2009"},{"content":"2009"},{"content":"2009"},{"content":"2009"},{"content":"2009"},{"content":"2009"},{"content":"2009"},{"content":"2009"},{"content":"2009"},{"content":"2009"},{"content":"2009"},{"content":"2009"},{"content":"2009"},{"content":"2009"},{"content":"2009"},{"content":"2009"},{"content":"2009"},{"content":"2009"},{"content":"2009"},{"content":"2009"},{"content":"2009"},{"content":"2009"},{"content":"2009"},{"content":"2009"},{"content":"2009"},{"content":"2009"},{"content":"2009"},{"content":"2009"},{"content":"2009"},{"content":"2009"},{"content":"2009"},{"content":"2009"},{"content":"2009"},{"content":"2009"},{"content":"2009"},{"content":"2009"},{"content":"2009"},{"content":"2009"},{"content":"2009"},{"content":"2009"},{"content":"2009"},{"content":"2009"},{"content":"2009"},{"content":"2009"},{"content":"2009"},{"content":"2009"},{"content":"2009"},{"content":"2009"},{"content":"2009"},{"content":"2009"},{"content":"2009"},{"content":"2009"},{"content":"2009"},{"content":"2009"},{"content":"2009"},{"content":"2009"},{"content":"2009"},{"content":"2009"},{"content":"2009"},{"content":"2009"},{"content":"2009"},{"content":"2009"},{"content":"2009"},{"content":"2009"},{"content":"2009"},{"content":"2009"},{"content":"2009"},{"content":"2009"},{"content":"2009"},{"content":"2009"},{"content":"2009"},{"content":"2009"},{"content":"2009"},{"content":"2009"},{"content":"2009"},{"content":"2009"},{"content":"2009"},{"content":"2009"},{"content":"2009"},{"content":"2009"},{"content":"2009"},{"content":"2009"},{"content":"2009"},{"content":"2009"},{"content":"2009"},{"content":"2009"},{"content":"2009"},{"content":"No Results"}]}}},"tableId":"Countries happiness index.html-0","results":{},"expectedResult":{"columns":{"0":true},"rows":{}},"originalDescription":{"hasContentTables":false,"hasRelevantTables":false}}