{"data":{"rows":{"0":{"cells":[{"content":"United States"},{"content":"11 In service"}]},"1":{"cells":[{"content":"United Kingdom"},{"content":"2 In service"}]},"2":{"cells":[{"content":"Italy"},{"content":"2 In service"}]},"3":{"cells":[{"content":"India"},{"content":"1 In service"}]},"4":{"cells":[{"content":"Russia"},{"content":"1 In service"}]},"5":{"cells":[{"content":"France"},{"content":"1 In service"}]},"6":{"cells":[{"content":"Brazil"},{"content":"1 In service"}]},"7":{"cells":[{"content":"Spain"},{"content":"1 In service"}]},"8":{"cells":[{"content":"Thailand"},{"content":"1 In service"}]},"9":{"cells":[{"content":"Argentina"},{"content":"Decommissioned"}]},"10":{"cells":[{"content":"Canada"},{"content":"Decommissioned"}]},"11":{"cells":[{"content":"Australia"},{"content":"Decommissioned"}]},"12":{"cells":[{"content":"Japan"},{"content":"Decommissioned"}]},"13":{"cells":[{"content":"Netherlands"},{"content":"Decommissioned"}]},"14":{"cells":[{"content":"No Results"},{"content":"No Results"}]}},"columns":{"0":{"cells":[{"content":"United States"},{"content":"United Kingdom"},{"content":"Italy"},{"content":"India"},{"content":"Russia"},{"content":"France"},{"content":"Brazil"},{"content":"Spain"},{"content":"Thailand"},{"content":"Argentina"},{"content":"Canada"},{"content":"Australia"},{"content":"Japan"},{"content":"Netherlands"},{"content":"No Results"}]},"1":{"cells":[{"content":"11 In service"},{"content":"2 In service"},{"content":"2 In service"},{"content":"1 In service"},{"content":"1 In service"},{"content":"1 In service"},{"content":"1 In service"},{"content":"1 In service"},{"content":"1 In service"},{"content":"Decommissioned"},{"content":"Decommissioned"},{"content":"Decommissioned"},{"content":"Decommissioned"},{"content":"Decommissioned"},{"content":"No Results"}]}}},"tableId":"Countries with aircraft carriers.html-0","results":{},"expectedResult":{"columns":{"0":true},"rows":{}},"originalDescription":{"hasContentTables":false,"hasRelevantTables":false}}