{"data":{"rows":{"0":{"cells":[{"content":"rank"},{"content":"Country"},{"content":"Gold"},{"content":"population (millions)"},{"content":"total gold /million pop"}]},"1":{"cells":[{"content":"1"},{"content":"?Finland"},{"content":"101"},{"content":"5.4"},{"content":"18.7"}]},"2":{"cells":[{"content":"2"},{"content":"Hungary"},{"content":"167"},{"content":"10.0"},{"content":"16.8"}]},"3":{"cells":[{"content":"3"},{"content":"Sweden"},{"content":"143"},{"content":"9.5"},{"content":"15.1"}]},"4":{"cells":[{"content":"4"},{"content":"Bahamas"},{"content":"5"},{"content":"0.4"},{"content":"14.1"}]},"5":{"cells":[{"content":"5"},{"content":"Norway"},{"content":"56"},{"content":"5.0"},{"content":"11.1"}]},"6":{"cells":[{"content":"6"},{"content":"Grenada"},{"content":"1"},{"content":"0.1"},{"content":"9.5"}]},"7":{"cells":[{"content":"7"},{"content":"East Germany #"},{"content":"153"},{"content":"16.1"},{"content":"9.5"}]},"8":{"cells":[{"content":"8"},{"content":"New Zealand"},{"content":"42"},{"content":"4.4"},{"content":"9.5"}]},"9":{"cells":[{"content":"9"},{"content":"Denmark"},{"content":"43"},{"content":"5.6"},{"content":"7.7"}]},"10":{"cells":[{"content":"10"},{"content":"Estonia"},{"content":"9"},{"content":"1.3"},{"content":"7.0"}]}},"columns":{"0":{"cells":[{"content":"rank"},{"content":"1"},{"content":"2"},{"content":"3"},{"content":"4"},{"content":"5"},{"content":"6"},{"content":"7"},{"content":"8"},{"content":"9"},{"content":"10"}]},"1":{"cells":[{"content":"Country"},{"content":"?Finland"},{"content":"Hungary"},{"content":"Sweden"},{"content":"Bahamas"},{"content":"Norway"},{"content":"Grenada"},{"content":"East Germany #"},{"content":"New Zealand"},{"content":"Denmark"},{"content":"Estonia"}]},"2":{"cells":[{"content":"Gold"},{"content":"101"},{"content":"167"},{"content":"143"},{"content":"5"},{"content":"56"},{"content":"1"},{"content":"153"},{"content":"42"},{"content":"43"},{"content":"9"}]},"3":{"cells":[{"content":"population (millions)"},{"content":"5.4"},{"content":"10.0"},{"content":"9.5"},{"content":"0.4"},{"content":"5.0"},{"content":"0.1"},{"content":"16.1"},{"content":"4.4"},{"content":"5.6"},{"content":"1.3"}]},"4":{"cells":[{"content":"total gold /million pop"},{"content":"18.7"},{"content":"16.8"},{"content":"15.1"},{"content":"14.1"},{"content":"11.1"},{"content":"9.5"},{"content":"9.5"},{"content":"9.5"},{"content":"7.7"},{"content":"7.0"}]}}},"tableId":"topendsports.com.html-0","results":{},"expectedResult":{"columns":{"1":true},"rows":{"0":true}},"originalDescription":{"hasContentTables":false,"hasRelevantTables":false}}