{"data":{"rows":{"0":{"cells":[{"content":"?Inflation figure"},{"content":"country/region"},{"content":"type"},{"content":"period"},{"content":"monthly basis"},{"content":"yearly basis"}]},"1":{"cells":[{"content":"?CPI Austria"},{"content":"Austria"},{"content":"cpi"},{"content":"january 2014"},{"content":"-0.916?%"},{"content":"1.501?%"}]},"2":{"cells":[{"content":"?CPI Belgium"},{"content":"Belgium"},{"content":"cpi"},{"content":"january 2014"},{"content":"0.139?%"},{"content":"1.136?%"}]},"3":{"cells":[{"content":"?CPI Brazil"},{"content":"Brazil"},{"content":"cpi"},{"content":"january 2014"},{"content":"0.550?%"},{"content":"5.585?%"}]},"4":{"cells":[{"content":"?CPI Canada"},{"content":"Canada"},{"content":"cpi"},{"content":"january 2014"},{"content":"0.326?%"},{"content":"1.484?%"}]},"5":{"cells":[{"content":"?CPI Chile"},{"content":"Chile"},{"content":"cpi"},{"content":"february 2014"},{"content":"0.482?%"},{"content":"3.395?%"}]},"6":{"cells":[{"content":"?CPI China"},{"content":"China"},{"content":"cpi"},{"content":"january 2014"},{"content":"1.000?%"},{"content":"2.507?%"}]},"7":{"cells":[{"content":"?CPI Czech Republic"},{"content":"Czech Republic"},{"content":"cpi"},{"content":"january 2014"},{"content":"0.081?%"},{"content":"0.163?%"}]},"8":{"cells":[{"content":"?CPI Denmark"},{"content":"Denmark"},{"content":"cpi"},{"content":"february 2014"},{"content":"0.694?%"},{"content":"0.539?%"}]},"9":{"cells":[{"content":"?CPI Estonia"},{"content":"Estonia"},{"content":"cpi"},{"content":"february 2014"},{"content":"0.153?%"},{"content":"0.615?%"}]},"10":{"cells":[{"content":"?CPI Finland"},{"content":"Finland"},{"content":"cpi"},{"content":"january 2014"},{"content":"-0.064?%"},{"content":"1.630?%"}]},"11":{"cells":[{"content":"?CPI France"},{"content":"France"},{"content":"cpi"},{"content":"january 2014"},{"content":"-0.556?%"},{"content":"0.650?%"}]},"12":{"cells":[{"content":"?CPI Germany"},{"content":"Germany"},{"content":"cpi"},{"content":"january 2014"},{"content":"-0.563?%"},{"content":"1.340?%"}]},"13":{"cells":[{"content":"?CPI Great Britain"},{"content":"Great Britain"},{"content":"cpi"},{"content":"january 2014"},{"content":"-0.627?%"},{"content":"1.849?%"}]},"14":{"cells":[{"content":"?CPI Greece"},{"content":"Greece"},{"content":"cpi"},{"content":"february 2014"},{"content":"-1.330?%"},{"content":"-1.150?%"}]},"15":{"cells":[{"content":"?CPI Hungary"},{"content":"Hungary"},{"content":"cpi"},{"content":"january 2014"},{"content":"0.371?%"},{"content":"-0.074?%"}]},"17":{"cells":[{"content":"?CPI India"},{"content":"India"},{"content":"cpi"},{"content":"january 2014"},{"content":"-0.837?%"},{"content":"7.240?%"}]},"16":{"cells":[{"content":"?CPI Iceland"},{"content":"Iceland"},{"content":"cpi"},{"content":"february 2014"},{"content":"0.680?%"},{"content":"2.124?%"}]},"19":{"cells":[{"content":"?CPI Ireland"},{"content":"Ireland"},{"content":"cpi"},{"content":"january 2014"},{"content":"-0.493?%"},{"content":"0.199?%"}]},"18":{"cells":[{"content":"?CPI Indonesia"},{"content":"Indonesia"},{"content":"cpi"},{"content":"february 2014"},{"content":"0.261?%"},{"content":"7.239?%"}]},"21":{"cells":[{"content":"?CPI Italy"},{"content":"Italy"},{"content":"cpi"},{"content":"february 2014"},{"content":"-0.093?%"},{"content":"0.468?%"}]},"20":{"cells":[{"content":"?CPI Israel"},{"content":"Israel"},{"content":"cpi"},{"content":"january 2014"},{"content":"-0.587?%"},{"content":"1.396?%"}]},"23":{"cells":[{"content":"?CPI Luxembourg"},{"content":"Luxembourg"},{"content":"cpi"},{"content":"february 2014"},{"content":"1.234?%"},{"content":"0.864?%"}]},"22":{"cells":[{"content":"?CPI Japan"},{"content":"Japan"},{"content":"cpi"},{"content":"january 2014"},{"content":"-0.198?%"},{"content":"1.410?%"}]},"25":{"cells":[{"content":"?CPI Norway"},{"content":"Norway"},{"content":"cpi"},{"content":"february 2014"},{"content":"0.518?%"},{"content":"2.105?%"}]},"24":{"cells":[{"content":"?CPI Mexico"},{"content":"Mexico"},{"content":"cpi"},{"content":"february 2014"},{"content":"0.253?%"},{"content":"4.234?%"}]},"27":{"cells":[{"content":"?CPI Portugal"},{"content":"Portugal"},{"content":"cpi"},{"content":"january 2014"},{"content":"-1.377?%"},{"content":"0.059?%"}]},"26":{"cells":[{"content":"?CPI Poland"},{"content":"Poland"},{"content":"cpi"},{"content":"december 2013"},{"content":"0.081?%"},{"content":"0.730?%"}]},"29":{"cells":[{"content":"?CPI Slovakia"},{"content":"Slovakia"},{"content":"cpi"},{"content":"january 2014"},{"content":"0.183?%"},{"content":"0.000?%"}]},"28":{"cells":[{"content":"?CPI Russia"},{"content":"Russia"},{"content":"cpi"},{"content":"january 2014"},{"content":"0.591?%"},{"content":"6.079?%"}]},"31":{"cells":[{"content":"?CPI South Africa"},{"content":"South Africa"},{"content":"cpi"},{"content":"january 2014"},{"content":"0.760?%"},{"content":"5.783?%"}]},"30":{"cells":[{"content":"?CPI Slovenia"},{"content":"Slovenia"},{"content":"cpi"},{"content":"january 2014"},{"content":"-0.630?%"},{"content":"0.822?%"}]},"34":{"cells":[{"content":"?CPI Sweden"},{"content":"Sweden"},{"content":"cpi"},{"content":"january 2014"},{"content":"-1.159?%"},{"content":"-0.196?%"}]},"35":{"cells":[{"content":"?CPI Switzerland"},{"content":"Switzerland"},{"content":"cpi"},{"content":"february 2014"},{"content":"0.099?%"},{"content":"-0.141?%"}]},"32":{"cells":[{"content":"?CPI South Korea"},{"content":"South Korea"},{"content":"cpi"},{"content":"february 2014"},{"content":"0.267?%"},{"content":"1.106?%"}]},"33":{"cells":[{"content":"?CPI Spain"},{"content":"Spain"},{"content":"cpi"},{"content":"january 2014"},{"content":"-1.330?%"},{"content":"0.199?%"}]},"38":{"cells":[{"content":"?CPI United States"},{"content":"United States"},{"content":"cpi"},{"content":"january 2014"},{"content":"0.372?%"},{"content":"1.579?%"}]},"39":{"cells":[{"content":"?HICP Austria"},{"content":"Austria"},{"content":"hicp"},{"content":"january 2014"},{"content":"-1.096?%"},{"content":"1.518?%"}]},"36":{"cells":[{"content":"?CPI the Netherlands"},{"content":"The Netherlands"},{"content":"cpi"},{"content":"february 2014"},{"content":"0.394?%"},{"content":"1.100?%"}]},"37":{"cells":[{"content":"?CPI Turkey"},{"content":"Turkey"},{"content":"cpi"},{"content":"february 2014"},{"content":"0.428?%"},{"content":"7.889?%"}]},"42":{"cells":[{"content":"?HICP Denmark"},{"content":"Denmark"},{"content":"hicp"},{"content":"january 2014"},{"content":"-0.171?%"},{"content":"0.777?%"}]},"43":{"cells":[{"content":"?HICP Estonia"},{"content":"Estonia"},{"content":"hicp"},{"content":"january 2014"},{"content":"0.182?%"},{"content":"1.573?%"}]},"40":{"cells":[{"content":"?HICP Belgium"},{"content":"Belgium"},{"content":"hicp"},{"content":"january 2014"},{"content":"-1.874?%"},{"content":"1.119?%"}]},"41":{"cells":[{"content":"?HICP Czech Republic"},{"content":"Czech Republic"},{"content":"hicp"},{"content":"january 2014"},{"content":"0.082?%"},{"content":"0.328?%"}]},"46":{"cells":[{"content":"?HICP France"},{"content":"France"},{"content":"hicp"},{"content":"january 2014"},{"content":"-0.641?%"},{"content":"0.765?%"}]},"47":{"cells":[{"content":"?HICP Germany"},{"content":"Germany"},{"content":"hicp"},{"content":"january 2014"},{"content":"-0.688?%"},{"content":"1.228?%"}]},"44":{"cells":[{"content":"?HICP Eurozone"},{"content":"Europe"},{"content":"hicp"},{"content":"december 2013"},{"content":"0.357?%"},{"content":"0.855?%"}]},"45":{"cells":[{"content":"?HICP Finland"},{"content":"Finland"},{"content":"hicp"},{"content":"january 2014"},{"content":"-0.058?%"},{"content":"1.875?%"}]},"51":{"cells":[{"content":"?HICP Iceland"},{"content":"Iceland"},{"content":"hicp"},{"content":"january 2014"},{"content":"-1.484?%"},{"content":"1.530?%"}]},"50":{"cells":[{"content":"?HICP Hungary"},{"content":"Hungary"},{"content":"hicp"},{"content":"january 2014"},{"content":"0.374?%"},{"content":"0.814?%"}]},"49":{"cells":[{"content":"?HICP Greece"},{"content":"Greece"},{"content":"hicp"},{"content":"january 2014"},{"content":"-0.949?%"},{"content":"-1.397?%"}]},"48":{"cells":[{"content":"?HICP Great Britain"},{"content":"Great Britain"},{"content":"hicp"},{"content":"january 2014"},{"content":"-0.627?%"},{"content":"1.849?%"}]},"55":{"cells":[{"content":"?HICP Poland"},{"content":"Poland"},{"content":"hicp"},{"content":"january 2014"},{"content":"0.080?%"},{"content":"0.560?%"}]},"54":{"cells":[{"content":"?HICP Luxembourg"},{"content":"Luxembourg"},{"content":"hicp"},{"content":"january 2014"},{"content":"-0.932?%"},{"content":"1.461?%"}]},"53":{"cells":[{"content":"?HICP Italy"},{"content":"Italy"},{"content":"hicp"},{"content":"january 2014"},{"content":"-2.082?%"},{"content":"0.599?%"}]},"52":{"cells":[{"content":"?HICP Ireland"},{"content":"Ireland"},{"content":"hicp"},{"content":"january 2014"},{"content":"-0.641?%"},{"content":"0.277?%"}]},"59":{"cells":[{"content":"?HICP Spain"},{"content":"Spain"},{"content":"hicp"},{"content":"january 2014"},{"content":"-1.850?%"},{"content":"0.277?%"}]},"58":{"cells":[{"content":"?HICP Slovenia"},{"content":"Slovenia"},{"content":"hicp"},{"content":"january 2014"},{"content":"-0.558?%"},{"content":"0.895?%"}]},"57":{"cells":[{"content":"?HICP Slovakia"},{"content":"Slovakia"},{"content":"hicp"},{"content":"january 2014"},{"content":"0.261?%"},{"content":"-0.049?%"}]},"56":{"cells":[{"content":"?HICP Portugal"},{"content":"Portugal"},{"content":"hicp"},{"content":"january 2014"},{"content":"-1.390?%"},{"content":"0.052?%"}]},"62":{"cells":[{"content":"?HICP Turkey"},{"content":"Turkey"},{"content":"hicp"},{"content":"january 2014"},{"content":"2.150?%"},{"content":"7.824?%"}]},"61":{"cells":[{"content":"?HICP the Netherlands"},{"content":"The Netherlands"},{"content":"hicp"},{"content":"january 2014"},{"content":"-0.630?%"},{"content":"0.797?%"}]},"60":{"cells":[{"content":"?HICP Sweden"},{"content":"Sweden"},{"content":"hicp"},{"content":"january 2014"},{"content":"-1.172?%"},{"content":"0.160?%"}]}},"columns":{"0":{"cells":[{"content":"?Inflation figure"},{"content":"?CPI Austria"},{"content":"?CPI Belgium"},{"content":"?CPI Brazil"},{"content":"?CPI Canada"},{"content":"?CPI Chile"},{"content":"?CPI China"},{"content":"?CPI Czech Republic"},{"content":"?CPI Denmark"},{"content":"?CPI Estonia"},{"content":"?CPI Finland"},{"content":"?CPI France"},{"content":"?CPI Germany"},{"content":"?CPI Great Britain"},{"content":"?CPI Greece"},{"content":"?CPI Hungary"},{"content":"?CPI Iceland"},{"content":"?CPI India"},{"content":"?CPI Indonesia"},{"content":"?CPI Ireland"},{"content":"?CPI Israel"},{"content":"?CPI Italy"},{"content":"?CPI Japan"},{"content":"?CPI Luxembourg"},{"content":"?CPI Mexico"},{"content":"?CPI Norway"},{"content":"?CPI Poland"},{"content":"?CPI Portugal"},{"content":"?CPI Russia"},{"content":"?CPI Slovakia"},{"content":"?CPI Slovenia"},{"content":"?CPI South Africa"},{"content":"?CPI South Korea"},{"content":"?CPI Spain"},{"content":"?CPI Sweden"},{"content":"?CPI Switzerland"},{"content":"?CPI the Netherlands"},{"content":"?CPI Turkey"},{"content":"?CPI United States"},{"content":"?HICP Austria"},{"content":"?HICP Belgium"},{"content":"?HICP Czech Republic"},{"content":"?HICP Denmark"},{"content":"?HICP Estonia"},{"content":"?HICP Eurozone"},{"content":"?HICP Finland"},{"content":"?HICP France"},{"content":"?HICP Germany"},{"content":"?HICP Great Britain"},{"content":"?HICP Greece"},{"content":"?HICP Hungary"},{"content":"?HICP Iceland"},{"content":"?HICP Ireland"},{"content":"?HICP Italy"},{"content":"?HICP Luxembourg"},{"content":"?HICP Poland"},{"content":"?HICP Portugal"},{"content":"?HICP Slovakia"},{"content":"?HICP Slovenia"},{"content":"?HICP Spain"},{"content":"?HICP Sweden"},{"content":"?HICP the Netherlands"},{"content":"?HICP Turkey"}]},"1":{"cells":[{"content":"country/region"},{"content":"Austria"},{"content":"Belgium"},{"content":"Brazil"},{"content":"Canada"},{"content":"Chile"},{"content":"China"},{"content":"Czech Republic"},{"content":"Denmark"},{"content":"Estonia"},{"content":"Finland"},{"content":"France"},{"content":"Germany"},{"content":"Great Britain"},{"content":"Greece"},{"content":"Hungary"},{"content":"Iceland"},{"content":"India"},{"content":"Indonesia"},{"content":"Ireland"},{"content":"Israel"},{"content":"Italy"},{"content":"Japan"},{"content":"Luxembourg"},{"content":"Mexico"},{"content":"Norway"},{"content":"Poland"},{"content":"Portugal"},{"content":"Russia"},{"content":"Slovakia"},{"content":"Slovenia"},{"content":"South Africa"},{"content":"South Korea"},{"content":"Spain"},{"content":"Sweden"},{"content":"Switzerland"},{"content":"The Netherlands"},{"content":"Turkey"},{"content":"United States"},{"content":"Austria"},{"content":"Belgium"},{"content":"Czech Republic"},{"content":"Denmark"},{"content":"Estonia"},{"content":"Europe"},{"content":"Finland"},{"content":"France"},{"content":"Germany"},{"content":"Great Britain"},{"content":"Greece"},{"content":"Hungary"},{"content":"Iceland"},{"content":"Ireland"},{"content":"Italy"},{"content":"Luxembourg"},{"content":"Poland"},{"content":"Portugal"},{"content":"Slovakia"},{"content":"Slovenia"},{"content":"Spain"},{"content":"Sweden"},{"content":"The Netherlands"},{"content":"Turkey"}]},"2":{"cells":[{"content":"type"},{"content":"cpi"},{"content":"cpi"},{"content":"cpi"},{"content":"cpi"},{"content":"cpi"},{"content":"cpi"},{"content":"cpi"},{"content":"cpi"},{"content":"cpi"},{"content":"cpi"},{"content":"cpi"},{"content":"cpi"},{"content":"cpi"},{"content":"cpi"},{"content":"cpi"},{"content":"cpi"},{"content":"cpi"},{"content":"cpi"},{"content":"cpi"},{"content":"cpi"},{"content":"cpi"},{"content":"cpi"},{"content":"cpi"},{"content":"cpi"},{"content":"cpi"},{"content":"cpi"},{"content":"cpi"},{"content":"cpi"},{"content":"cpi"},{"content":"cpi"},{"content":"cpi"},{"content":"cpi"},{"content":"cpi"},{"content":"cpi"},{"content":"cpi"},{"content":"cpi"},{"content":"cpi"},{"content":"cpi"},{"content":"hicp"},{"content":"hicp"},{"content":"hicp"},{"content":"hicp"},{"content":"hicp"},{"content":"hicp"},{"content":"hicp"},{"content":"hicp"},{"content":"hicp"},{"content":"hicp"},{"content":"hicp"},{"content":"hicp"},{"content":"hicp"},{"content":"hicp"},{"content":"hicp"},{"content":"hicp"},{"content":"hicp"},{"content":"hicp"},{"content":"hicp"},{"content":"hicp"},{"content":"hicp"},{"content":"hicp"},{"content":"hicp"},{"content":"hicp"}]},"3":{"cells":[{"content":"period"},{"content":"january 2014"},{"content":"january 2014"},{"content":"january 2014"},{"content":"january 2014"},{"content":"february 2014"},{"content":"january 2014"},{"content":"january 2014"},{"content":"february 2014"},{"content":"february 2014"},{"content":"january 2014"},{"content":"january 2014"},{"content":"january 2014"},{"content":"january 2014"},{"content":"february 2014"},{"content":"january 2014"},{"content":"february 2014"},{"content":"january 2014"},{"content":"february 2014"},{"content":"january 2014"},{"content":"january 2014"},{"content":"february 2014"},{"content":"january 2014"},{"content":"february 2014"},{"content":"february 2014"},{"content":"february 2014"},{"content":"december 2013"},{"content":"january 2014"},{"content":"january 2014"},{"content":"january 2014"},{"content":"january 2014"},{"content":"january 2014"},{"content":"february 2014"},{"content":"january 2014"},{"content":"january 2014"},{"content":"february 2014"},{"content":"february 2014"},{"content":"february 2014"},{"content":"january 2014"},{"content":"january 2014"},{"content":"january 2014"},{"content":"january 2014"},{"content":"january 2014"},{"content":"january 2014"},{"content":"december 2013"},{"content":"january 2014"},{"content":"january 2014"},{"content":"january 2014"},{"content":"january 2014"},{"content":"january 2014"},{"content":"january 2014"},{"content":"january 2014"},{"content":"january 2014"},{"content":"january 2014"},{"content":"january 2014"},{"content":"january 2014"},{"content":"january 2014"},{"content":"january 2014"},{"content":"january 2014"},{"content":"january 2014"},{"content":"january 2014"},{"content":"january 2014"},{"content":"january 2014"}]},"4":{"cells":[{"content":"monthly basis"},{"content":"-0.916?%"},{"content":"0.139?%"},{"content":"0.550?%"},{"content":"0.326?%"},{"content":"0.482?%"},{"content":"1.000?%"},{"content":"0.081?%"},{"content":"0.694?%"},{"content":"0.153?%"},{"content":"-0.064?%"},{"content":"-0.556?%"},{"content":"-0.563?%"},{"content":"-0.627?%"},{"content":"-1.330?%"},{"content":"0.371?%"},{"content":"0.680?%"},{"content":"-0.837?%"},{"content":"0.261?%"},{"content":"-0.493?%"},{"content":"-0.587?%"},{"content":"-0.093?%"},{"content":"-0.198?%"},{"content":"1.234?%"},{"content":"0.253?%"},{"content":"0.518?%"},{"content":"0.081?%"},{"content":"-1.377?%"},{"content":"0.591?%"},{"content":"0.183?%"},{"content":"-0.630?%"},{"content":"0.760?%"},{"content":"0.267?%"},{"content":"-1.330?%"},{"content":"-1.159?%"},{"content":"0.099?%"},{"content":"0.394?%"},{"content":"0.428?%"},{"content":"0.372?%"},{"content":"-1.096?%"},{"content":"-1.874?%"},{"content":"0.082?%"},{"content":"-0.171?%"},{"content":"0.182?%"},{"content":"0.357?%"},{"content":"-0.058?%"},{"content":"-0.641?%"},{"content":"-0.688?%"},{"content":"-0.627?%"},{"content":"-0.949?%"},{"content":"0.374?%"},{"content":"-1.484?%"},{"content":"-0.641?%"},{"content":"-2.082?%"},{"content":"-0.932?%"},{"content":"0.080?%"},{"content":"-1.390?%"},{"content":"0.261?%"},{"content":"-0.558?%"},{"content":"-1.850?%"},{"content":"-1.172?%"},{"content":"-0.630?%"},{"content":"2.150?%"}]},"5":{"cells":[{"content":"yearly basis"},{"content":"1.501?%"},{"content":"1.136?%"},{"content":"5.585?%"},{"content":"1.484?%"},{"content":"3.395?%"},{"content":"2.507?%"},{"content":"0.163?%"},{"content":"0.539?%"},{"content":"0.615?%"},{"content":"1.630?%"},{"content":"0.650?%"},{"content":"1.340?%"},{"content":"1.849?%"},{"content":"-1.150?%"},{"content":"-0.074?%"},{"content":"2.124?%"},{"content":"7.240?%"},{"content":"7.239?%"},{"content":"0.199?%"},{"content":"1.396?%"},{"content":"0.468?%"},{"content":"1.410?%"},{"content":"0.864?%"},{"content":"4.234?%"},{"content":"2.105?%"},{"content":"0.730?%"},{"content":"0.059?%"},{"content":"6.079?%"},{"content":"0.000?%"},{"content":"0.822?%"},{"content":"5.783?%"},{"content":"1.106?%"},{"content":"0.199?%"},{"content":"-0.196?%"},{"content":"-0.141?%"},{"content":"1.100?%"},{"content":"7.889?%"},{"content":"1.579?%"},{"content":"1.518?%"},{"content":"1.119?%"},{"content":"0.328?%"},{"content":"0.777?%"},{"content":"1.573?%"},{"content":"0.855?%"},{"content":"1.875?%"},{"content":"0.765?%"},{"content":"1.228?%"},{"content":"1.849?%"},{"content":"-1.397?%"},{"content":"0.814?%"},{"content":"1.530?%"},{"content":"0.277?%"},{"content":"0.599?%"},{"content":"1.461?%"},{"content":"0.560?%"},{"content":"0.052?%"},{"content":"-0.049?%"},{"content":"0.895?%"},{"content":"0.277?%"},{"content":"0.160?%"},{"content":"0.797?%"},{"content":"7.824?%"}]}}},"tableId":"www.global-rates.com-inflation.html-0","results":{},"expectedResult":{"columns":{"1":true},"rows":{"0":true}},"originalDescription":{"hasContentTables":false,"hasRelevantTables":false}}