{"data":{"rows":{"0":{"cells":[{"content":"?"},{"content":"Country"},{"content":"Total Emissions (Million Metric Tons of CO2)"},{"content":"Per Capita Emissions (Tons/Capita)"}]},"1":{"cells":[{"content":"1."},{"content":"China"},{"content":"6534"},{"content":"4.91"}]},"2":{"cells":[{"content":"2."},{"content":"United States"},{"content":"5833"},{"content":"19.18"}]},"3":{"cells":[{"content":"3."},{"content":"Russia"},{"content":"1729"},{"content":"12.29"}]},"4":{"cells":[{"content":"4."},{"content":"India"},{"content":"1495"},{"content":"1.31"}]},"5":{"cells":[{"content":"5."},{"content":"Japan"},{"content":"1214"},{"content":"9.54"}]},"6":{"cells":[{"content":"6."},{"content":"Germany"},{"content":"829"},{"content":"10.06"}]},"7":{"cells":[{"content":"7."},{"content":"Canada"},{"content":"574"},{"content":"17.27"}]},"8":{"cells":[{"content":"8."},{"content":"United Kingdom"},{"content":"572"},{"content":"9.38"}]},"9":{"cells":[{"content":"9."},{"content":"Korea, South"},{"content":"542"},{"content":"11.21"}]},"10":{"cells":[{"content":"10."},{"content":"Iran"},{"content":"511"},{"content":"7.76"}]},"11":{"cells":[{"content":"11."},{"content":"Saudi Arabia"},{"content":"466"},{"content":"16.56"}]},"12":{"cells":[{"content":"12."},{"content":"Italy"},{"content":"455"},{"content":"7.82"}]},"13":{"cells":[{"content":"13."},{"content":"South Africa"},{"content":"451"},{"content":"9.25"}]},"14":{"cells":[{"content":"14."},{"content":"Mexico"},{"content":"445"},{"content":"4.04"}]},"15":{"cells":[{"content":"15."},{"content":"Australia"},{"content":"437"},{"content":"20.82"}]},"17":{"cells":[{"content":"17."},{"content":"Brazil"},{"content":"428"},{"content":"2.18"}]},"16":{"cells":[{"content":"16."},{"content":"Indonesia"},{"content":"434"},{"content":"1.83"}]},"19":{"cells":[{"content":"19."},{"content":"Spain"},{"content":"359"},{"content":"8.86"}]},"18":{"cells":[{"content":"18."},{"content":"France"},{"content":"415"},{"content":"6.48"}]},"20":{"cells":[{"content":"20."},{"content":"Ukraine"},{"content":"350"},{"content":"7.61"}]}},"columns":{"0":{"cells":[{"content":"?"},{"content":"1."},{"content":"2."},{"content":"3."},{"content":"4."},{"content":"5."},{"content":"6."},{"content":"7."},{"content":"8."},{"content":"9."},{"content":"10."},{"content":"11."},{"content":"12."},{"content":"13."},{"content":"14."},{"content":"15."},{"content":"16."},{"content":"17."},{"content":"18."},{"content":"19."},{"content":"20."}]},"1":{"cells":[{"content":"Country"},{"content":"China"},{"content":"United States"},{"content":"Russia"},{"content":"India"},{"content":"Japan"},{"content":"Germany"},{"content":"Canada"},{"content":"United Kingdom"},{"content":"Korea, South"},{"content":"Iran"},{"content":"Saudi Arabia"},{"content":"Italy"},{"content":"South Africa"},{"content":"Mexico"},{"content":"Australia"},{"content":"Indonesia"},{"content":"Brazil"},{"content":"France"},{"content":"Spain"},{"content":"Ukraine"}]},"2":{"cells":[{"content":"Total Emissions (Million Metric Tons of CO2)"},{"content":"6534"},{"content":"5833"},{"content":"1729"},{"content":"1495"},{"content":"1214"},{"content":"829"},{"content":"574"},{"content":"572"},{"content":"542"},{"content":"511"},{"content":"466"},{"content":"455"},{"content":"451"},{"content":"445"},{"content":"437"},{"content":"434"},{"content":"428"},{"content":"415"},{"content":"359"},{"content":"350"}]},"3":{"cells":[{"content":"Per Capita Emissions (Tons/Capita)"},{"content":"4.91"},{"content":"19.18"},{"content":"12.29"},{"content":"1.31"},{"content":"9.54"},{"content":"10.06"},{"content":"17.27"},{"content":"9.38"},{"content":"11.21"},{"content":"7.76"},{"content":"16.56"},{"content":"7.82"},{"content":"9.25"},{"content":"4.04"},{"content":"20.82"},{"content":"1.83"},{"content":"2.18"},{"content":"6.48"},{"content":"8.86"},{"content":"7.61"}]}}},"tableId":"www.ucsusa.org.html-0","results":{},"expectedResult":{"columns":{"1":true},"rows":{"0":true}},"originalDescription":{"hasContentTables":false,"hasRelevantTables":false}}