{"filename":"67367570_3354779367295660538","uri":"http://www.cheap-international-phone-cards.info/sticallingcards/sti-el-presidente-california.html","arcfile":"common-crawl/parse-output/segment/1346823845675/1346864495132_34.arc.gz","arcfilePosition":67367570,"hasContentTables":true,"hasRelevantTables":false,"contentTables":[{"start":7823,"end":23952,"content":true,"relevant":false,"avgColCount":29.0,"colStdDeviation":0.0,"avgRowCount":4.0,"rowStdDeviation":0.0,"avgCellLength":15.0,"cellLengthStdDeviation":7.675532105557782,"rowCLC":0.5372862009525298,"colCLC":1.6541395386222963,"linkPercentage":0.2413793103448276,"formPercentage":0.0,"imagePercentage":0.0,"emptyPercentage":0.0,"digitPercentage":0.0,"textPercentage":0.7586206896551724,"rowCTC":2.0689655172413794,"colCTC":3.9310344827586206}]}