{"filename":"83777795_2108237019080868675","uri":"http://www.continental.com/cms/en-US/travel/Pages/CheckedBaggage.aspx","arcfile":"common-crawl/parse-output/segment/1346823845675/1346864649841_344.arc.gz","arcfilePosition":83777795,"hasContentTables":true,"hasRelevantTables":false,"contentTables":[{"start":30359,"end":36870,"content":true,"relevant":false,"avgColCount":15.4,"colStdDeviation":4.800000000000001,"avgRowCount":9.058823529411764,"rowStdDeviation":0.23529411764705876,"avgCellLength":4.0,"cellLengthStdDeviation":10.025940380806208,"rowCLC":2.7215686274509805,"colCLC":1.294397759103641,"linkPercentage":0.0,"formPercentage":0.0,"imagePercentage":0.006493506493506494,"emptyPercentage":0.006493506493506494,"digitPercentage":0.0,"textPercentage":0.987012987012987,"rowCTC":8.823529411764707,"colCTC":8.941176470588236}]}