{"filename":"94850921_599110073134306522","uri":"http://www.indianauction.co.nz/browse/business-industry/","arcfile":"common-crawl/parse-output/segment/1346823845675/1346864480261_2.arc.gz","arcfilePosition":94850921,"hasContentTables":true,"hasRelevantTables":false,"contentTables":[{"start":46918,"end":73159,"content":true,"relevant":false,"avgColCount":37.0,"colStdDeviation":0.0,"avgRowCount":7.0,"rowStdDeviation":0.0,"avgCellLength":13.0,"cellLengthStdDeviation":17.320619532911085,"rowCLC":-0.2688710688710689,"colCLC":NaN,"linkPercentage":0.277992277992278,"formPercentage":0.0,"imagePercentage":0.0,"emptyPercentage":0.03861003861003861,"digitPercentage":0.03861003861003861,"textPercentage":0.6447876447876448,"rowCTC":2.027027027027027,"colCTC":5.8108108108108105}]}